pyrtlib/__init__.py
pyrtlib/absorption_model.py
pyrtlib/rt_equation.py
pyrtlib/tb_spectrum.py
pyrtlib/utils.py
pyrtlib/version.py
pyrtlib/weighting_functions.py
pyrtlib/_lineshape/__init__.py
pyrtlib/_lineshape/h2o_lineshape.nc
pyrtlib/_lineshape/h2oll.py
pyrtlib/_lineshape/o2_lineshape.nc
pyrtlib/_lineshape/o2ll.py
pyrtlib/_lineshape/o3_lineshape.nc
pyrtlib/_lineshape/o3ll.py
pyrtlib/apiwebservices/__init__.py
pyrtlib/apiwebservices/eps_sandbox.py
pyrtlib/apiwebservices/erafive.py
pyrtlib/apiwebservices/igra2.py
pyrtlib/apiwebservices/webservices.py
pyrtlib/apiwebservices/wyomingupperair.py
pyrtlib/climatology/__init__.py
pyrtlib/climatology/atmospheric_profiles.py
pyrtlib/climatology/extrapolation.py
pyrtlib/climatology/gas_minor.dat
pyrtlib/climatology/gas_trace.dat
pyrtlib/climatology/midlatitude_summer.dat
pyrtlib/climatology/midlatitude_winter.dat
pyrtlib/climatology/subarctic_summer.dat
pyrtlib/climatology/subarctic_winter.dat
pyrtlib/climatology/tropical.dat
pyrtlib/climatology/us_standard.dat
pyrtlib/uncertainty/__init__.py
pyrtlib/uncertainty/absmod_uncertainty.py
pyrtlib/uncertainty/covariance_matrix/__init__.py
pyrtlib/uncertainty/covariance_matrix/R17/Cov_parameters_Cimini_et_al_2018_V1.1.nc
pyrtlib/uncertainty/covariance_matrix/R17/Cov_parameters_Cimini_et_al_2019_V2.0.nc
pyrtlib/uncertainty/covariance_matrix/R19/Cov_parameters_Gallucci_et_al_ACPD_2023_V1.0.nc
pyrtlib-1.1.1.dist-info/LICENSE
pyrtlib-1.1.1.dist-info/METADATA
pyrtlib-1.1.1.dist-info/WHEEL
pyrtlib-1.1.1.dist-info/top_level.txt
pyrtlib-1.1.1.dist-info/RECORD
